test/usefulFunction.py
usefulFunctionPlan11-0.0.1.dist-info/METADATA
usefulFunctionPlan11-0.0.1.dist-info/WHEEL
usefulFunctionPlan11-0.0.1.dist-info/top_level.txt
usefulFunctionPlan11-0.0.1.dist-info/RECORD
